GANDLF/__init__.py
GANDLF/config_manager.py
GANDLF/inference_manager.py
GANDLF/logger.py
GANDLF/logging_config.yaml
GANDLF/parseConfig.py
GANDLF/training_manager.py
GANDLF/version.py
GANDLF/anonymize/__init__.py
GANDLF/anonymize/convert_to_nifti.py
GANDLF/cli/__init__.py
GANDLF/cli/config_generator.py
GANDLF/cli/data_split_saver.py
GANDLF/cli/deploy.py
GANDLF/cli/generate_metrics.py
GANDLF/cli/huggingface_hub_handler.py
GANDLF/cli/main_run.py
GANDLF/cli/patch_extraction.py
GANDLF/cli/post_training_model_optimization.py
GANDLF/cli/preprocess_and_save.py
GANDLF/cli/recover_config.py
GANDLF/compute/__init__.py
GANDLF/compute/forward_pass.py
GANDLF/compute/generic.py
GANDLF/compute/inference_loop.py
GANDLF/compute/loss_and_metric.py
GANDLF/compute/step.py
GANDLF/compute/training_loop.py
GANDLF/configuration/__init__.py
GANDLF/configuration/default_config.py
GANDLF/configuration/differential_privacy_config.py
GANDLF/configuration/exclude_parameters.py
GANDLF/configuration/model_config.py
GANDLF/configuration/nested_training_config.py
GANDLF/configuration/optimizer_config.py
GANDLF/configuration/parameters_config.py
GANDLF/configuration/patch_sampler_config.py
GANDLF/configuration/post_processing_config.py
GANDLF/configuration/pre_processing_config.py
GANDLF/configuration/scheduler_config.py
GANDLF/configuration/user_defined_config.py
GANDLF/configuration/utils.py
GANDLF/configuration/validators.py
GANDLF/data/ImagesFromDataFrame.py
GANDLF/data/__init__.py
GANDLF/data/inference_dataloader_histopath.py
GANDLF/data/lightning_datamodule.py
GANDLF/data/augmentation/__init__.py
GANDLF/data/augmentation/blur_enhanced.py
GANDLF/data/augmentation/hed_augs.py
GANDLF/data/augmentation/noise_enhanced.py
GANDLF/data/augmentation/rgb_augs.py
GANDLF/data/augmentation/rotations.py
GANDLF/data/augmentation/wrap_torchio.py
GANDLF/data/patch_miner/__init__.py
GANDLF/data/patch_miner/opm/__init__.py
GANDLF/data/patch_miner/opm/patch.py
GANDLF/data/patch_miner/opm/patch_manager.py
gandlf-0.1.5.dist-info/licenses/LICENSE
gandlf-0.1.5.dist-info/METADATA
gandlf-0.1.5.dist-info/WHEEL
gandlf-0.1.5.dist-info/entry_points.txt
gandlf-0.1.5.dist-info/top_level.txt
gandlf-0.1.5.dist-info/RECORD
