Metadata-Version: 2.4
Name: GANDLF
Version: 0.1.5
Summary: PyTorch-based framework that handles segmentation/regression/classification using various DL architectures for medical imaging.
Author: MLCommons
Author-email: gandlf@mlcommons.org
License: Apache-2.0
Keywords: semantic,segmentation,regression,classification,data-augmentation,medical-imaging,clinical-workflows,deep-learning,pytorch
Classifier: Development Status :: 3 - Alpha
Classifier: Intended Audience :: Science/Research
Classifier: License :: OSI Approved :: Apache Software License
Classifier: Natural Language :: English
Classifier: Operating System :: OS Independent
Classifier: Programming Language :: Python :: 3.10
Classifier: Programming Language :: Python :: 3.11
Classifier: Programming Language :: Python :: 3.12
Classifier: Topic :: Scientific/Engineering :: Medical Science Apps.
Requires-Python: >3.9, <3.13
License-File: LICENSE
Requires-Dist: torch==2.7.1
Requires-Dist: black==23.11.0
Requires-Dist: lightning==2.5.2
Requires-Dist: numpy==1.26.4
Requires-Dist: scipy
Requires-Dist: SimpleITK!=2.0.*
Requires-Dist: SimpleITK!=2.2.1
Requires-Dist: torchvision
Requires-Dist: tqdm
Requires-Dist: torchio==0.19.6
Requires-Dist: pandas>=2.0.0
Requires-Dist: scikit-learn>=0.23.2
Requires-Dist: scikit-image>=0.19.1
Requires-Dist: setuptools
Requires-Dist: seaborn
Requires-Dist: pyyaml
Requires-Dist: matplotlib
Requires-Dist: gdown==5.1.0
Requires-Dist: overrides==7.7.0
Requires-Dist: pytest
Requires-Dist: coverage
Requires-Dist: pytest-cov
Requires-Dist: psutil
Requires-Dist: medcam
Requires-Dist: opencv-python
Requires-Dist: torchmetrics==1.1.2
Requires-Dist: zarr==2.10.3
Requires-Dist: numcodecs<0.16.0
Requires-Dist: pydicom
Requires-Dist: onnx
Requires-Dist: torchinfo==1.7.0
Requires-Dist: segmentation-models-pytorch==0.4.0
Requires-Dist: ACSConv==0.1.1
Requires-Dist: requests>=2.32.2
Requires-Dist: docker
Requires-Dist: dicom-anonymizer==1.0.12
Requires-Dist: twine
Requires-Dist: keyring
Requires-Dist: monai==1.4.0
Requires-Dist: click==8.1.8
Requires-Dist: deprecated
Requires-Dist: packaging==24.0
Requires-Dist: colorlog
Requires-Dist: opacus==1.5.2
Requires-Dist: huggingface-hub==0.25.1
Requires-Dist: openslide-bin
Requires-Dist: openslide-python==1.4.1
Requires-Dist: lion-pytorch==0.2.2
Requires-Dist: pydantic==2.10.6
Requires-Dist: panoptica>=1.4.1
Dynamic: author
Dynamic: author-email
Dynamic: classifier
Dynamic: description
Dynamic: description-content-type
Dynamic: keywords
Dynamic: license
Dynamic: license-file
Dynamic: requires-dist
Dynamic: requires-python
Dynamic: summary
